{"version": 0.6, "generator": "Overpass API 0.7.62.7 375dc00a", "osm3s": {"timestamp_osm_base": "2025-07-07T02:10:57Z", "copyright": "The data included in this document is from www.openstreetmap.org. The data is made available under ODbL."}, "elements": [{"type": "node", "id": 1289408213, "lat": 16.4596758, "lon": -95.0849359}, {"type": "node", "id": 4992679021, "lat": 16.3395853, "lon": -95.2255154, "tags": {"amenity": "hospital", "name": "Centro de Salud SS", "name:es": "Centro de Salud SS"}}, {"type": "node", "id": 5091696657, "lat": 16.4327285, "lon": -95.0195868, "tags": {"amenity": "hospital", "name": "Cl\u00ednica Catalina"}}, {"type": "node", "id": 5091696658, "lat": 16.4315759, "lon": -95.0190504, "tags": {"amenity": "hospital", "name": "Guendanabani"}}, {"type": "node", "id": 5102155750, "lat": 16.2025259, "lon": -95.201801}, {"type": "node", "id": 5102155751, "lat": 16.2026141, "lon": -95.2017615}, {"type": "node", "id": 5102155752, "lat": 16.201957, "lon": -95.2018882}, {"type": "node", "id": 5102155753, "lat": 16.2021406, "lon": -95.2019675}, {"type": "node", "id": 5102155754, "lat": 16.2019408, "lon": -95.2019519}, {"type": "node", "id": 5102155755, "lat": 16.2017794, "lon": -95.2019074}, {"type": "node", "id": 5102155756, "lat": 16.2021224, "lon": -95.2019338}, {"type": "node", "id": 5102155757, "lat": 16.2025989, "lon": -95.2018212}, {"type": "node", "id": 5102155758, "lat": 16.20234, "lon": -95.2020225}, {"type": "node", "id": 5102155759, "lat": 16.2024611, "lon": -95.2020559}, {"type": "node", "id": 5102155760, "lat": 16.2028352, "lon": -95.2012509}, {"type": "node", "id": 5102155761, "lat": 16.2026994, "lon": -95.201785}, {"type": "node", "id": 5102155762, "lat": 16.2018688, "lon": -95.2015559}, {"type": "node", "id": 5102155763, "lat": 16.2020046, "lon": -95.2010219}, {"type": "node", "id": 5108066746, "lat": 16.1747058, "lon": -95.1977118}, {"type": "node", "id": 5108066748, "lat": 16.1744274, "lon": -95.1973093}, {"type": "node", "id": 5108066749, "lat": 16.1744705, "lon": -95.1977375}, {"type": "node", "id": 5109393725, "lat": 16.1745652, "lon": -95.1973806}, {"type": "node", "id": 5109393726, "lat": 16.1745566, "lon": -95.1972952}, {"type": "node", "id": 5109393727, "lat": 16.1746714, "lon": -95.197369}, {"type": "node", "id": 5114453054, "lat": 16.1756442, "lon": -95.197331}, {"type": "node", "id": 5114453055, "lat": 16.1757742, "lon": -95.1973072}, {"type": "node", "id": 5114453056, "lat": 16.1758008, "lon": -95.1974646}, {"type": "node", "id": 5114453057, "lat": 16.1756143, "lon": -95.1975167}, {"type": "node", "id": 5114453058, "lat": 16.1756319, "lon": -95.1972585}, {"type": "node", "id": 5114453059, "lat": 16.1758263, "lon": -95.1972241}, {"type": "node", "id": 5114453060, "lat": 16.1758785, "lon": -95.1975332}, {"type": "node", "id": 5114453061, "lat": 16.175625, "lon": -95.1975797}, {"type": "node", "id": 5122101136, "lat": 16.206222, "lon": -95.1941067}, {"type": "node", "id": 5122101137, "lat": 16.2062315, "lon": -95.1940163}, {"type": "node", "id": 5122101138, "lat": 16.2062772, "lon": -95.1940215}, {"type": "node", "id": 5122101139, "lat": 16.2062814, "lon": -95.1939816}, {"type": "node", "id": 5122101140, "lat": 16.2061956, "lon": -95.1939718}, {"type": "node", "id": 5122101141, "lat": 16.2061742, "lon": -95.1941757}, {"type": "node", "id": 5122101142, "lat": 16.2063562, "lon": -95.1941964}, {"type": "node", "id": 5122101143, "lat": 16.2064259, "lon": -95.1939558}, {"type": "node", "id": 5122101144, "lat": 16.206354, "lon": -95.1939476}, {"type": "node", "id": 5122101145, "lat": 16.2063359, "lon": -95.1941196}, {"type": "node", "id": 5126715467, "lat": 16.2063611, "lon": -95.1941497}, {"type": "node", "id": 5126715468, "lat": 16.206405, "lon": -95.1941547}, {"type": "node", "id": 5132749897, "lat": 16.1756616, "lon": -95.1975081}, {"type": "node", "id": 5132749898, "lat": 16.1756587, "lon": -95.1974906}, {"type": "node", "id": 5132749899, "lat": 16.1756921, "lon": -95.1972487}, {"type": "node", "id": 5132749900, "lat": 16.1756456, "lon": -95.197256}, {"type": "node", "id": 5132749901, "lat": 16.1756888, "lon": -95.1972287}, {"type": "node", "id": 5132749902, "lat": 16.1756425, "lon": -95.1972371}, {"type": "node", "id": 5220678924, "lat": 16.3195975, "lon": -95.2398348, "tags": {"amenity": "hospital", "name": "Cruz roja", "name:en": "Red cross", "opening_hours": "24/7"}}, {"type": "node", "id": 5828290072, "lat": 16.4337331, "lon": -95.0180142, "tags": {"amenity": "hospital", "healthcare": "hospital"}}, {"type": "node", "id": 8683030369, "lat": 16.4596912, "lon": -95.0866123}, {"type": "node", "id": 8978734757, "lat": 16.4614221, "lon": -95.0849438}, {"type": "node", "id": 8978734758, "lat": 16.4614454, "lon": -95.0865808}, {"type": "node", "id": 12383620936, "lat": 16.2238896, "lon": -95.2125058, "tags": {"addr:postcode": "70613", "addr:street": "Calle Francisco I. Madero", "amenity": "hospital", "name": "Casa de Salud"}}, {"type": "node", "id": 12384470150, "lat": 16.1818297, "lon": -95.1949136}, {"type": "node", "id": 12384470151, "lat": 16.1822029, "lon": -95.1950646}, {"type": "node", "id": 12384470152, "lat": 16.1823571, "lon": -95.194615}, {"type": "node", "id": 12384470153, "lat": 16.181987, "lon": -95.1944641}, {"type": "node", "id": 12384618491, "lat": 16.202841, "lon": -95.1940265}, {"type": "node", "id": 12384618492, "lat": 16.202867, "lon": -95.1922916}, {"type": "node", "id": 12384618493, "lat": 16.2012323, "lon": -95.1922952}, {"type": "node", "id": 12384618494, "lat": 16.201243, "lon": -95.1941237}, {"type": "node", "id": 12392119293, "lat": 16.1874329, "lon": -95.2046703, "tags": {"addr:postcode": "70650", "addr:street": "Tocuela", "amenity": "hospital", "name": "Centro De Salud Colonia Morelos"}}, {"type": "node", "id": 12392584095, "lat": 16.2060747, "lon": -95.2172868, "tags": {"addr:postcode": "70610", "addr:street": "Calle Yucat\u00e1n", "amenity": "hospital", "healthcare": "hospital", "name": "Centro De Salud Colonia Hugo Mayoral"}}, {"type": "node", "id": 12394236539, "lat": 16.2238999, "lon": -95.2059464, "tags": {"addr:postcode": "70613", "addr:street": "Gladiolas", "amenity": "hospital", "email": "capasits_salina_cruz@hotmail.com", "healthcare": "hospital", "name": "Centro Ambulatorio Para La Prevencion y Atencion Del Sida e Infecciones De Transmision Sexual"}}, {"type": "way", "id": 524260018, "nodes": [5102155753, 5102155758, 5102155759, 5102155750, 5102155757, 5102155751, 5102155761, 5102155760, 5102155763, 5102155762, 5102155755, 5102155754, 5102155752, 5102155756, 5102155753], "tags": {"addr:city": "Salina Cruz", "addr:postcode": "70610", "addr:state": "Oax", "addr:street": "Trans\u00edsmica", "amenity": "hospital", "healthcare": "hospital", "name": "Hospital general de zona con medicina familiar n\u00famero 02"}}, {"type": "way", "id": 524999442, "nodes": [5108066746, 5109393727, 5109393725, 5109393726, 5108066748, 5108066749, 5108066746], "tags": {"addr:postcode": "70690", "addr:street": "Calle Virgilio Uribe", "amenity": "hospital", "healthcare": "hospital", "name": "Hospital General Naval De Salina Cruz"}}, {"type": "way", "id": 525795261, "nodes": [5114453061, 5114453060, 5114453059, 5132749899, 5132749901, 5132749902, 5132749900, 5114453058, 5114453054, 5114453055, 5114453056, 5132749898, 5132749897, 5114453057, 5114453061], "tags": {"amenity": "hospital", "building": "yes", "emergency": "yes", "name": "Hospital Naval De Salina Cruz"}}, {"type": "way", "id": 526796067, "nodes": [5122101145, 5122101144, 5122101143, 5126715468, 5126715467, 5122101142, 5122101141, 5122101140, 5122101139, 5122101138, 5122101137, 5122101136, 5122101145], "tags": {"addr:city": "Salina Cruz3", "addr:postcode": "70610", "addr:street": "Avenida Francisco Villa", "amenity": "hospital", "email": "sancarm_scx@yahoo.comm.mx", "healthcare": "hospital", "name": "Sanatorio Del Carmen", "phone": "9717141180"}}, {"type": "way", "id": 970252164, "nodes": [8978734757, 8978734758, 8683030369, 1289408213, 8978734757], "tags": {"amenity": "hospital", "healthcare": "hospital"}}, {"type": "way", "id": 1338867280, "nodes": [12384470150, 12384470151, 12384470152, 12384470153, 12384470150], "tags": {"addr:city": "Salina Cruz", "addr:postcode": "70600", "addr:state": "Oaxaca", "addr:street": "Calle Tuxpan", "amenity": "hospital", "email": "csusalinacruz@gmail.com", "healthcare": "hospital", "name": "Hospital General de Sauld SSA"}}, {"type": "way", "id": 1338882376, "nodes": [12384618491, 12384618492, 12384618493, 12384618494, 12384618491], "tags": {"addr:city": "Salina Cruz", "addr:postcode": "70620", "addr:state": "Oaxaca", "addr:street": "Calle Francisco Villa", "amenity": "hospital", "healthcare": "hospital", "name": "Hospital General de Pemex"}}]}